pybluez2-0.46.data/purelib/bluetooth/__init__.py
pybluez2-0.46.data/purelib/bluetooth/address.py
pybluez2-0.46.data/purelib/bluetooth/btcommon.py
pybluez2-0.46.data/purelib/bluetooth/device.py
pybluez2-0.46.data/purelib/bluetooth/docstrings.py
pybluez2-0.46.data/purelib/bluetooth/native_socket.py
pybluez2-0.46.data/purelib/bluetooth/version.py
pybluez2-0.46.data/purelib/bluetooth/macos/IOBluetooth.py
pybluez2-0.46.data/purelib/bluetooth/macos/__init__.py
pybluez2-0.46.data/purelib/bluetooth/macos/discovery.py
pybluez2-0.46.data/purelib/bluetooth/macos/loop.py
pybluez2-0.46.data/purelib/bluetooth/macos/util.py
pybluez2-0.46.data/purelib/bluetooth/macos/btsocket/__init__.py
pybluez2-0.46.data/purelib/bluetooth/macos/btsocket/btsocket.py
pybluez2-0.46.data/purelib/bluetooth/macos/btsocket/connection.py
pybluez2-0.46.data/purelib/bluetooth/macos/btsocket/delegate.py
pybluez2-0.46.dist-info/LICENSE
pybluez2-0.46.dist-info/METADATA
pybluez2-0.46.dist-info/WHEEL
pybluez2-0.46.dist-info/eager_resources.txt
pybluez2-0.46.dist-info/top_level.txt
pybluez2-0.46.dist-info/zip-safe
pybluez2-0.46.dist-info/RECORD
