Metadata-Version: 2.1
Name: pybluez2
Version: 0.46
Summary: Bluetooth Python extension module
Home-page: https://github.com/airgproducts/pybluez2
Author: airgproducts
Author-email: hello@airgproducts.com
Maintainer: airgproducts
License: GPL
Platform: UNKNOWN
Classifier: Development Status :: 4 - Beta
Classifier: License :: OSI Approved :: GNU General Public License (GPL)
Classifier: Programming Language :: Python
Classifier: Programming Language :: Python :: 3
Classifier: Programming Language :: Python :: 3.6
Classifier: Programming Language :: Python :: 3.7
Classifier: Programming Language :: Python :: 3.8
Classifier: Programming Language :: Python :: 3.9
Classifier: Programming Language :: Python :: 3 :: Only
Classifier: Topic :: Communications
Requires-Python: >3.6
Requires-Dist: pyobjc-core (>=6)
Requires-Dist: pyobjc-framework-Cocoa (>=6)
Requires-Dist: pyobjc-framework-libdispatch
